{"cameraMode":{"drawMode":0,"name":"Shaded","section":"Shading Mode"},"sceneLighting":true,"audioPlay":false,"sceneViewState":{"m_AlwaysRefresh":false,"showFog":true,"showSkybox":true,"showFlares":true,"showImageEffects":true,"showParticleSystems":true,"showVisualEffectGraphs":true,"m_FxEnabled":true},"in2DMode":false,"pivot":{"x":27.810733795166017,"y":20.31734848022461,"z":27.12232780456543},"rotation":{"x":-0.14454664289951325,"y":0.43123164772987368,"z":-0.07026339322328568,"w":-0.8879566192626953},"size":7.768811225891113,"orthographic":false}